hitoshura25_gemini_workflow_bridge/__init__.py
hitoshura25_gemini_workflow_bridge/cache_manager.py
hitoshura25_gemini_workflow_bridge/cli.py
hitoshura25_gemini_workflow_bridge/codebase_loader.py
hitoshura25_gemini_workflow_bridge/gemini_client.py
hitoshura25_gemini_workflow_bridge/generator.py
hitoshura25_gemini_workflow_bridge/resources.py
hitoshura25_gemini_workflow_bridge/server.py
hitoshura25_gemini_workflow_bridge/prompts/fact_extraction_system_prompt.txt
hitoshura25_gemini_workflow_bridge/prompts/pattern_extraction_prompt.txt
hitoshura25_gemini_workflow_bridge/prompts/validation_system_prompt.txt
hitoshura25_gemini_workflow_bridge/tests/__init__.py
hitoshura25_gemini_workflow_bridge/tests/conftest.py
hitoshura25_gemini_workflow_bridge/tests/test_cache_manager.py
hitoshura25_gemini_workflow_bridge/tests/test_gemini_client.py
hitoshura25_gemini_workflow_bridge/tests/test_generator.py
hitoshura25_gemini_workflow_bridge/tests/test_server.py
hitoshura25_gemini_workflow_bridge/tests/test_setup_workflows.py
hitoshura25_gemini_workflow_bridge/tools/__init__.py
hitoshura25_gemini_workflow_bridge/tools/check_consistency.py
hitoshura25_gemini_workflow_bridge/tools/find_code_by_intent.py
hitoshura25_gemini_workflow_bridge/tools/generate_command.py
hitoshura25_gemini_workflow_bridge/tools/generate_workflow.py
hitoshura25_gemini_workflow_bridge/tools/list_patterns.py
hitoshura25_gemini_workflow_bridge/tools/query_codebase.py
hitoshura25_gemini_workflow_bridge/tools/setup_workflows.py
hitoshura25_gemini_workflow_bridge/tools/trace_feature.py
hitoshura25_gemini_workflow_bridge/tools/validate_spec.py
hitoshura25_gemini_workflow_bridge/tools/workflow_templates.py
hitoshura25_gemini_workflow_bridge/utils/__init__.py
hitoshura25_gemini_workflow_bridge/utils/prompt_loader.py
hitoshura25_gemini_workflow_bridge/utils/token_counter.py
hitoshura25_gemini_workflow_bridge/utils/validation.py
hitoshura25_gemini_workflow_bridge/workflows/feature_template.md
hitoshura25_gemini_workflow_bridge-0.6.1.dist-info/licenses/LICENSE
hitoshura25_gemini_workflow_bridge-0.6.1.dist-info/METADATA
hitoshura25_gemini_workflow_bridge-0.6.1.dist-info/WHEEL
hitoshura25_gemini_workflow_bridge-0.6.1.dist-info/entry_points.txt
hitoshura25_gemini_workflow_bridge-0.6.1.dist-info/top_level.txt
hitoshura25_gemini_workflow_bridge-0.6.1.dist-info/RECORD
