Metadata-Version: 2.4
Name: hitoshura25-gemini-workflow-bridge
Version: 0.6.1
Summary: MCP server that bridges Claude Code to Gemini CLI for workflow tasks like codebase analysis, specification creation, and code review
Author-email: Vinayak Menon <hitoshura.25@gmail.com>
License: Apache-2.0
Project-URL: Homepage, https://github.com/hitoshura25/gemini-workflow-bridge-mcp
Project-URL: Repository, https://github.com/hitoshura25/gemini-workflow-bridge-mcp
Project-URL: Issues, https://github.com/hitoshura25/gemini-workflow-bridge-mcp/issues
Classifier: Development Status :: 3 - Alpha
Classifier: Intended Audience :: Developers
Classifier: License :: OSI Approved :: Apache Software License
Classifier: Programming Language :: Python :: 3
Classifier: Programming Language :: Python :: 3.11
Classifier: Programming Language :: Python :: 3.12
Classifier: Programming Language :: Python :: 3.13
Requires-Python: >=3.11
License-File: LICENSE
Requires-Dist: mcp<2.0.0,>=1.0.0
Requires-Dist: python-dotenv>=1.0.0
Requires-Dist: gitpython>=3.1.0
Requires-Dist: pathspec>=0.12.0
Provides-Extra: dev
Requires-Dist: pytest>=7.0.0; extra == "dev"
Requires-Dist: pytest-asyncio>=0.21.0; extra == "dev"
Requires-Dist: pytest-mock>=3.10.0; extra == "dev"
Requires-Dist: pytest-cov>=4.0.0; extra == "dev"
Dynamic: license-file
